AUTHORS
CHANGES
INSTALL
LICENSE
MANIFEST.in
Makefile
ez_setup.py
gpl.txt
setup.py
Pocoo.egg-info/PKG-INFO
Pocoo.egg-info/SOURCES.txt
Pocoo.egg-info/dependency_links.txt
Pocoo.egg-info/not-zip-safe
Pocoo.egg-info/requires.txt
Pocoo.egg-info/top_level.txt
pocoo/__init__.py
pocoo/application.py
pocoo/context.py
pocoo/db.py
pocoo/exceptions.py
pocoo/filetemplates.py
pocoo/http.py
pocoo/ihook.py
pocoo/management.py
pocoo/settings.py
pocoo/template.py
pocoo/pkg/__init__.py
pocoo/pkg/core/__init__.py
pocoo/pkg/core/acl.py
pocoo/pkg/core/auth.py
pocoo/pkg/core/bbcode.py
pocoo/pkg/core/cache.py
pocoo/pkg/core/captcha.py
pocoo/pkg/core/cobalt.py
pocoo/pkg/core/db.py
pocoo/pkg/core/feeds.py
pocoo/pkg/core/forms.py
pocoo/pkg/core/forum.py
pocoo/pkg/core/i18n.py
pocoo/pkg/core/l10n.py
pocoo/pkg/core/package.conf
pocoo/pkg/core/pages.py
pocoo/pkg/core/remotecall.py
pocoo/pkg/core/restformat.py
pocoo/pkg/core/search.py
pocoo/pkg/core/session.py
pocoo/pkg/core/simplehtml.py
pocoo/pkg/core/smilies.py
pocoo/pkg/core/statustracking.py
pocoo/pkg/core/template.py
pocoo/pkg/core/textfmt.py
pocoo/pkg/core/user.py
pocoo/pkg/core/usersettings.py
pocoo/pkg/core/validators.py
pocoo/pkg/core/static/AJS/AJS.js
pocoo/pkg/core/static/AJS/AJS_minify.py
pocoo/pkg/core/static/AJS/referece.html
pocoo/pkg/core/static/AJS/examples/ajax_yahoo_img_search.html
pocoo/pkg/core/static/AJS/examples/deferred_delicious.html
pocoo/pkg/core/static/AJS/examples/drag_n_drop.html
pocoo/pkg/core/static/AJS/examples/reziseable_textarea.html
pocoo/pkg/core/static/AJS/examples/sortable_list.html
pocoo/pkg/core/static/AJS/static/script.js
pocoo/pkg/core/static/AJS/static/style.css
pocoo/pkg/core/static/default/img/background.png
pocoo/pkg/core/static/default/img/background_admin.png
pocoo/pkg/core/static/default/img/background_post.png
pocoo/pkg/core/static/default/img/build.sh
pocoo/pkg/core/static/default/img/content_background.png
pocoo/pkg/core/static/default/img/indicator.gif
pocoo/pkg/core/static/default/img/navigation.png
pocoo/pkg/core/static/default/img/bbcode/bold.png
pocoo/pkg/core/static/default/img/bbcode/code.png
pocoo/pkg/core/static/default/img/bbcode/img.png
